lfl_admin/__init__.py
lfl_admin/common/__init__.py
lfl_admin/common/management/__init__.py
lfl_admin/common/management/commands/__init__.py
lfl_admin/common/management/commands/check_unbounded_image_files.py
lfl_admin/common/management/commands/fill_image_ftypes.py
lfl_admin/common/management/commands/fill_image_ftypes1.py
lfl_admin/common/migrations/0001_initial.py
lfl_admin/common/migrations/0002_site_lfl_images_date.py
lfl_admin/common/migrations/0003_auto_20210217_1647.py
lfl_admin/common/migrations/0004_remove_site_lfl_images_date.py
lfl_admin/common/migrations/0005_site_lfl_images_date.py
lfl_admin/common/migrations/0006_auto_20210217_1651.py
lfl_admin/common/migrations/0007_images.py
lfl_admin/common/migrations/0008_auto_20210218_0023.py
lfl_admin/common/migrations/0009_image_types.py
lfl_admin/common/migrations/0010_images_image_type.py
lfl_admin/common/migrations/0011_auto_20210218_0437.py
lfl_admin/common/migrations/0012_links.py
lfl_admin/common/migrations/0013_text_informations.py
lfl_admin/common/migrations/0014_menus.py
lfl_admin/common/migrations/0015_posts.py
lfl_admin/common/migrations/0016_auto_20210218_1253.py
lfl_admin/common/migrations/0017_delete_menus.py
lfl_admin/common/migrations/0018_edited_by.py
lfl_admin/common/migrations/0019_remove_edited_by_edited_by.py
lfl_admin/common/migrations/0020_auto_20210219_0916.py
lfl_admin/common/migrations/0021_auto_20210301_1105.py
lfl_admin/common/migrations/0022_auto_20210301_1433.py
lfl_admin/common/migrations/0023_auto_20210303_0942.py
lfl_admin/common/migrations/0024_delete_edited_by.py
lfl_admin/common/migrations/0025_auto_20210309_0847.py
lfl_admin/common/migrations/0026_auto_20210402_0508.py
lfl_admin/common/migrations/0027_posts_props.py
lfl_admin/common/migrations/0028_alter_posts_props.py
lfl_admin/common/migrations/0029_all_tables.py
lfl_admin/common/migrations/0030_delete_all_tables.py
lfl_admin/common/migrations/0031_all_tables.py
lfl_admin/common/migrations/0032_delete_all_tables.py
lfl_admin-0.0.9.dist-info/LICENSE.txt
lfl_admin-0.0.9.dist-info/METADATA
lfl_admin-0.0.9.dist-info/WHEEL
lfl_admin-0.0.9.dist-info/entry_points.txt
lfl_admin-0.0.9.dist-info/top_level.txt
lfl_admin-0.0.9.dist-info/RECORD
