Metadata-Version: 2.1
Name: lfl-admin
Version: 0.0.9
Summary: ISC Python common project
Home-page: UNKNOWN
Author: Andrey Yudin
Author-email: uandrew1965@gmail.com
License: UNKNOWN
Project-URL: Source, https://github.com/lfl-ru/lfl-admin.git
Keywords: isc setuptools development common kaf-pas
Platform: UNKNOWN
Classifier: Development Status :: 3 - Alpha
Classifier: Intended Audience :: Developers
Classifier: Topic :: Software Development :: Build Tools
Classifier: License :: OSI Approved :: MIT License
Classifier: Programming Language :: Python :: 3.8
Classifier: Programming Language :: Python :: 3.7
Classifier: Programming Language :: Python :: 3.6
Requires-Python: >=3.6
